{
  "model": "gemma3:12b",
  "chapter": 3,
  "chapter_ja": "高頻度データの実証的性質",
  "chapter_en": "Empirical Properties of High-Frequency Data",
  "pdf_page": 81,
  "printed_page": "66",
  "source_chars": 635,
  "translation_chars": 347,
  "elapsed_seconds": 11.326,
  "created_at": "2026-06-20T21:01:39",
  "translation": "66                                               3 高頻度データの経験的特性\n\n\n\n\n図3.29　10秒間の取引数と累積取引量、二乗対数リターンと取引数、二乗対数リターンと累積取引量、二乗対数リターンとビッド・アスク・スプレッド、取引数とビッド・アスク・スプレッド、リターンとアスク・ビッド・デスの不均衡、取引数とデプス、および累積取引量とデプスのクロス・自己相関関数。JP Morgan（NYSE）、Microsoft（NASDAQ）、およびDeutsche Telekom（XETRA）について。サンプル期間は、JP MorganとMicrosoftについては2009年6月、Deutsche Telekomについては2010年9月である。"
}
